pymarlzooplus/__init__.py
pymarlzooplus/main.py
pymarlzooplus/run.py
pymarlzooplus/search.py
pymarlzooplus/components/__init__.py
pymarlzooplus/components/action_selectors.py
pymarlzooplus/components/episode_buffer.py
pymarlzooplus/components/episodic_memory_buffer.py
pymarlzooplus/components/epsilon_schedules.py
pymarlzooplus/components/lrn_knn.py
pymarlzooplus/components/proportional.py
pymarlzooplus/components/standarize_stream.py
pymarlzooplus/components/sum_tree.py
pymarlzooplus/components/transforms.py
pymarlzooplus/config/__init__.py
pymarlzooplus/config/default.yaml
pymarlzooplus/config/algs/__init__.py
pymarlzooplus/config/algs/cds.yaml
pymarlzooplus/config/algs/coma.yaml
pymarlzooplus/config/algs/coma_ns.yaml
pymarlzooplus/config/algs/emc.yaml
pymarlzooplus/config/algs/eoi.yaml
pymarlzooplus/config/algs/happo.yaml
pymarlzooplus/config/algs/ia2c.yaml
pymarlzooplus/config/algs/ia2c_ns.yaml
pymarlzooplus/config/algs/ippo.yaml
pymarlzooplus/config/algs/ippo_ns.yaml
pymarlzooplus/config/algs/iql.yaml
pymarlzooplus/config/algs/iql_ns.yaml
pymarlzooplus/config/algs/maa2c.yaml
pymarlzooplus/config/algs/maa2c_ns.yaml
pymarlzooplus/config/algs/maddpg.yaml
pymarlzooplus/config/algs/maddpg_ns.yaml
pymarlzooplus/config/algs/mappo.yaml
pymarlzooplus/config/algs/mappo_ns.yaml
pymarlzooplus/config/algs/maser.yaml
pymarlzooplus/config/algs/mat_dec.yaml
pymarlzooplus/config/algs/qmix.yaml
pymarlzooplus/config/algs/qmix_ns.yaml
pymarlzooplus/config/algs/qplex.yaml
pymarlzooplus/config/algs/vdn.yaml
pymarlzooplus/config/algs/vdn_ns.yaml
pymarlzooplus/config/envs/__init__.py
pymarlzooplus/config/envs/boxpushing.yaml
pymarlzooplus/config/envs/capturetarget.yaml
pymarlzooplus/config/envs/gymma.yaml
pymarlzooplus/config/envs/overcooked.yaml
pymarlzooplus/config/envs/pettingzoo.yaml
pymarlzooplus/config/envs/pressureplate.yaml
pymarlzooplus/controllers/__init__.py
pymarlzooplus/controllers/basic_controller.py
pymarlzooplus/controllers/cds_controller.py
pymarlzooplus-1.0.0.dist-info/LICENSE
pymarlzooplus-1.0.0.dist-info/METADATA
pymarlzooplus-1.0.0.dist-info/WHEEL
pymarlzooplus-1.0.0.dist-info/top_level.txt
pymarlzooplus-1.0.0.dist-info/RECORD
