Metadata-Version: 2.1
Name: pymarlzooplus
Version: 1.0.0
Summary: An extended benchmarking of multi-agent reinforcement learning algorithms
Home-page: https://github.com/AILabDsUnipi/pymarlzooplus
Author: AILabDsUnipi
Author-email: gp.papadopoulos.george@gmail.com
License: Apache License 2.0
Requires-Python: >=3.8
License-File: LICENSE
Requires-Dist: gymnasium
Requires-Dist: matplotlib
Requires-Dist: numpy
Requires-Dist: PyYAML
Requires-Dist: sacred
Requires-Dist: six
Requires-Dist: tensorboard-logger
Requires-Dist: pandas
Requires-Dist: torch
Requires-Dist: scikit-learn
Requires-Dist: pyglet==1.5.27
Requires-Dist: tqdm
Requires-Dist: pettingzoo[all]
Requires-Dist: seaborn
Requires-Dist: networkx
Requires-Dist: rware>1.0.3
Requires-Dist: lbforaging>1.1.1
Requires-Dist: torchvision
Requires-Dist: albumentations==1.4.18
Requires-Dist: transformers
Requires-Dist: autorom
Requires-Dist: pygame
Requires-Dist: scipy
Requires-Dist: dill
Requires-Dist: ipython
Requires-Dist: ipywidgets
Requires-Dist: opencv-python-headless
